v4docker/__init__.py
v4docker/app.py
v4docker/bin/__init__.py
v4docker-0.1.2.data/scripts/v4docker
v4docker-0.1.2.dist-info/LICENSE
v4docker-0.1.2.dist-info/METADATA
v4docker-0.1.2.dist-info/WHEEL
v4docker-0.1.2.dist-info/top_level.txt
v4docker-0.1.2.dist-info/RECORD
