Metadata-Version: 2.1
Name: v4docker
Version: 0.1.2
Summary: Simple TUI to manage docker images
Home-page: https://github.com/lethe3000/v4docker
Author: lethe3000
Author-email: lethe30003000@gmail.com
License: UNKNOWN
Platform: UNKNOWN
Classifier: Programming Language :: Python :: 3
Classifier: License :: OSI Approved :: MIT License
Classifier: Operating System :: OS Independent
Requires-Python: >=3.6
Requires-Dist: docker (==4.0.2)
Requires-Dist: picotui (==1.0.1)
